CHANGELOG.txt
LICENCE.txt
MANIFEST.in
README.txt
setup.py
multil.egg-info/PKG-INFO
multil.egg-info/SOURCES.txt
multil.egg-info/dependency_links.txt
multil.egg-info/top_level.txt
multithread/__init__.py