Metadata-Version: 2.1
Name: multil
Version: 0.0.1
Summary: run multiple def programs at once using threads
Home-page: 
Author: 
Author-email: 
License: MIT
Keywords: multi
Classifier: Development Status :: 5 - Production/Stable
Classifier: Intended Audience :: Education
Classifier: Operating System :: Microsoft :: Windows :: Windows 10
Classifier: License :: OSI Approved :: MIT License
Classifier: Programming Language :: Python :: 3
License-File: LICENCE.txt
